[
    {"activity":"Go out for ice cream.", "season":"Spring Summer", "minPrice":5, "timeOfDay":"Afternoon Evening"},
    {"activity":"Go get dinner together", "season":"Any season", "minPrice":10, "timeOfDay":"Evening"},  
    {"activity":"Go bowling", "season":"Any season", "minPrice":10, "timeOfDay":"Afternoon Evening"},
    {"activity":"Go get breakfast together", "season":"Any season", "minPrice":10, "timeOfDay":"Morning"},
    {"activity":"Eat lunch together", "season":"Any season", "minPrice":10, "timeOfDay":"Afternoon"},
    {"activity":"Go swimming together", "season":"Any season", "minPrice":10, "timeOfDay":"Afternoon Evening"},
    {"activity":"Go on a walk together", "season":"Any season", "minPrice":0, "timeOfDay":"Early morning Morning Afternoon Evening"},
    {"activity":"Eat dinner at a fancy restaurant", "season":"Any season", "minPrice":25, "timeOfDay":"Afternoon Evening"},
    {"activity":"See a movie", "season":"Any season", "minPrice":25, "timeOfDay":"Afternoon Evening Night"},
    {"activity":"Go stargazing", "season":"Spring Summer Fall", "minPrice":0, "timeOfDay":"Night"},
    {"activity":"Go sledding", "season":"Winter", "minPrice":0, "timeOfDay":"Morning Afternoon Evening"},
    {"activity":"Go snow shoeing", "season":"Winter", "minPrice":0, "timeOfDay":"Morning Afternoon Evening"},
    {"activity":"Build a snowman", "season":"Winter", "minPrice":0, "timeOfDay":"Morning Afternoon Evening"},
    {"activity":"See some Christmas lights", "season":"Winter", "minPrice":0, "timeOfDay":"Evening Night"},
    {"activity":"Get some hot cocoa", "season":"Winter", "minPrice":5, "timeOfDay":"Afternoon Evening Night"},
    {"activity":"Have a movie night", "season":"Any season", "minPrice":0, "timeOfDay":"Evening Night"},
    {"activity":"See the Fall leaves", "season":"Fall", "minPrice":0, "timeOfDay":"Morning Afternoon Evening"},
    {"activity":"Fly a kite together", "season":"Spring Summer Fall", "minPrice":5, "timeOfDay":"Morning Afternoon Evening"},
    {"activity":"Try a new restaurant", "season":"Any season", "minPrice":10, "timeOfDay":"Morning Afternoon Evening"},
    {"activity":"Play tourist in your hometown and see what others would see when they visit", "season":"Any season", "minPrice":0, "timeOfDay":"Morning Afternoon Evening"},
    {"activity":"Make breakfast for each other", "season":"Any season", "minPrice":10, "timeOfDay":"Early morning morning"},
    {"activity":"Make lunch for each other", "season":"Any season", "minPrice":10, "timeOfDay":"Afternoon"},
    {"activity":"Make dinner for each other", "season":"Any season", "minPrice":10, "timeOfDay":"Evening Night"},
    {"activity":"Try making a new recipe together", "season":"Any season", "minPrice":10, "timeOfDay":"Any time"},
    {"activity":"Go on a picnic", "season":"Spring Summer Fall", "minPrice":10, "timeOfDay":"Morning Afternoon Evening"},
    {"activity":"Go on a hike", "season":"Spring Summer Fall", "minPrice":10, "timeOfDay":"Early morning Morning Afternoon Evening"},
    {"activity":"Go skiing", "season":"Winter", "minPrice":30, "timeOfDay":"Early morning Morning Afternoon Evening"},
    {"activity":"Play a board game", "season":"Any season", "minPrice":0, "timeOfDay":"Any time"},
    {"activity":"Have a campfire and roast hot dogs or make s'mores", "season":"Any season", "minPrice":5, "timeOfDay":"Evening Night"},
    {"activity":"Take a day trip and see some interesting places together", "season":"Any season", "minPrice":5, "timeOfDay":"Any time"},
    {"activity":"Learn a new skill together.", "season":"Any season", "minPrice":0, "timeOfDay":"Any time"},
    {"activity":"Look through old photos together", "season":"Any season", "minPrice":0, "timeOfDay":"Any time"},
    {"activity":"Learn to dance", "season":"Any season", "minPrice":0, "timeOfDay":"Any time"},
    {"activity":"Volunteer together and serve someone else.", "season":"Any season", "minPrice":0, "timeOfDay":"Morning Afternoon Evening"},
    {"activity":"Visit the aquarium", "season":"Any season", "minPrice":25, "timeOfDay":"Morning Afternoon Evening"},
    {"activity":"Visit the zoo", "season":"Any season", "minPrice":25, "timeOfDay":"Morning Afternoon Evening"},
    {"activity":"See a comedy show", "season":"Any season", "minPrice":25, "timeOfDay":"Evening Night"},
    {"activity":"Go rock climbing", "season":"Any season", "minPrice":25, "timeOfDay":"Morning Afternoon Evening"},
    {"activity":"Take a cooking class", "season":"Any season", "minPrice":25, "timeOfDay":"Morning Afternoon Evening"},
    {"activity":"Go to a water park", "season":"Summer", "minPrice":25, "timeOfDay":"Morning Afternoon Evening"},
    {"activity":"See a drive-in movie", "season":"Summer Spring Fall", "minPrice":25, "timeOfDay":"Evening Night"},
    {"activity":"Go to the arcade", "season":"Any season", "minPrice":5, "timeOfDay":"Afternoon Evening"},
    {"activity":"Go to the library and choose books for each other", "season":"Any season", "minPrice":0, "timeOfDay":"Morning Afternoon Evening"},
    {"activity":"Watch a sports game", "season":"Any season", "minPrice":10, "timeOfDay":"Morning Afternoon Evening"},
    {"activity":"Go ice skating", "season":"Any season", "minPrice":15, "timeOfDay":"Morning Afternoon Evening"},
    {"activity":"Play lazer tag", "season":"Any season", "minPrice":15, "timeOfDay":"Morning Afternoon Evening"},
    {"activity":"Drive some go-karts", "season":"Any season", "minPrice":30, "timeOfDay":"Morning Afternoon Evening"},
    {"activity":"Build a bucket list", "season":"Any season", "minPrice":0, "timeOfDay":"Any time"},
    {"activity":"Go to a haunted house", "season":"Fall", "minPrice":30, "timeOfDay":"Evening Night"},
    {"activity":"Go to a corn maze", "season":"Fall", "minPrice":20, "timeOfDay":"Evening Night"},
    {"activity":"Eat at a food truck", "season":"Spring Summer Fall", "minPrice":20, "timeOfDay":"Afternoon Evening"},
    {"activity":"Buy some finger paints, get a white tarp, and finger paint with each other", "season":"Any season", "minPrice":5, "timeOfDay":"Any time"},
    {"activity":"Get milkshakes", "season":"Any season", "minPrice":8, "timeOfDay":"Afternoon Evening"},
    {"activity":"Go to a museum", "season":"Any season", "minPrice":15, "timeOfDay":"Morning Afternoon Evening"},
    {"activity":"Go to the planetarium", "season":"Any season", "minPrice":0, "timeOfDay":"Morning Afternoon Evening"},
    {"activity":"Go biking", "season":"Spring Summer Fall", "minPrice":0, "timeOfDay":"Morning Afternoon Evening"},
    {"activity":"Go to a concert", "season":"Any season", "minPrice":50, "timeOfDay":"Evening Night"},
    {"activity":"See some live music", "season":"Any season", "minPrice":0, "timeOfDay":"Evening Night"},
    {"activity":"Go country swing dancing", "season":"Any season", "minPrice":10, "timeOfDay":"Evening Night"},
    {"activity":"Go salsa dancing", "season":"Any season", "minPrice":10, "timeOfDay":"Evening Night"},
    {"activity":"Go on a drive", "season":"Any season", "minPrice":0, "timeOfDay":"Morning Evening Night"},
    {"activity":"See a play", "season":"Any season", "minPrice":20, "timeOfDay":"Evening"},
    {"activity":"Go to an escape room", "season":"Any season", "minPrice":30, "timeOfDay":"Afternoon Evening"},
    {"activity":"Go indoor surfing, or real surfing if you're near the beach!", "season":"Any season", "minPrice":20, "timeOfDay":"Morning Afternoon Evening"},
    {"activity":"Play racquetball", "season":"Any season", "minPrice":10, "timeOfDay":"Morning Afternoon Evening"},
    {"activity":"Go roller skating", "season":"Any season", "minPrice":10, "timeOfDay":"Afternoon Evening Night"},
    {"activity":"Go to a trampoline park", "season":"Any season", "minPrice":25, "timeOfDay":"Afternoon Evening"},
    {"activity":"Go river rafting or tubing", "season":"Spring Summer", "minPrice":25, "timeOfDay":"Morning Afternoon Evening"},
    {"activity":"Go axe throwing", "season":"Any season", "minPrice":15, "timeOfDay":"Morning Afternoon Evening"},
    {"activity":"Paint together", "season":"Any season", "minPrice":5, "timeOfDay":"Any time"},
    {"activity":"Go to a rodeo", "season":"Summer", "minPrice":20, "timeOfDay":"Afternoon Evening"},
    {"activity":"Pick and carve pumpkins", "season":"Fall", "minPrice":5, "timeOfDay":"Any time"},
    {"activity":"Go on a ghost tour", "season":"Any season", "minPrice":25, "timeOfDay":"Afternoon, Evening"},
    {"activity":"Go geocaching", "season":"Any season", "minPrice":0, "timeOfDay":"Afternoon, Evening"},
    {"activity":"Shop at a thrift store", "season":"Any season", "minPrice":5, "timeOfDay":"Morning Afternoon, Evening"},
    {"activity":"Go window shopping", "season":"Any season", "minPrice":0, "timeOfDay":"Morning Afternoon, Evening"},
    {"activity":"Learn some history and go on tours in your city", "season":"Any season", "minPrice":0, "timeOfDay":"Morning Afternoon, Evening"},
    {"activity":"Work on a puzzle", "season":"Any season", "minPrice":0, "timeOfDay":"Any time"},
    {"activity":"Play a video game", "season":"Any season", "minPrice":0, "timeOfDay":"Any time"},
    {"activity":"Pick up a tie-dye kit at a craft store and Tie-dye some clothing", "season":"Any season", "minPrice":10, "timeOfDay":"Any time"},
    {"activity":"Watch the sun rise", "season":"Spring Summer Fall", "minPrice":0, "timeOfDay":"Evening"},
    {"activity":"Go to a local arts presentation like a play, poetry, dance, ect.", "season":"Spring Summer Fall", "minPrice":0, "timeOfDay":"Evening"},
    {"activity":"Go on a run together", "season":"Spring Summer Fall", "minPrice":0, "timeOfDay":"Any time"},
    {"activity":"Find a pottery class", "season":"Any season", "minPrice":20, "timeOfDay":"Any time"},
    {"activity":"Walk a dog together", "season":"Any season", "minPrice":0, "timeOfDay":"Any time"},
    {"activity":"Tour a botanical garden", "season":"Spring Summer", "minPrice":0, "timeOfDay":"Morning, Afternoon, Evening"},
    {"activity":"Visit an art gallery", "season":"Any season", "minPrice":0, "timeOfDay":"Morning, Afternoon, Evening"},
    {"activity":"Go to a carnival", "season":"Spring Summer", "minPrice":0, "timeOfDay":"Afternoon, Evening"},
    {"activity":"Play miniature golf", "season":"Spring Summer", "minPrice":10, "timeOfDay":"Afternoon, Evening"},
    {"activity":"Have a game night and invite another couple or two", "season":"Any season", "minPrice":0, "timeOfDay":"Evening, Night"},
    {"activity":"Have a water fight", "season":"Summer", "minPrice":0, "timeOfDay":"Morning, Afternoon, Evening"},
    {"activity":"Go camping, you can even just go in your own backyard", "season":"Summer", "minPrice":0, "timeOfDay":"Afternoon, Evening, Night"},
    {"activity":"Go to a VR Café", "season":"Any season", "minPrice":20, "timeOfDay":"Afternoon, Evening"},
    {"activity":"Go longboarding", "season":"Spring Summer Fall", "minPrice":0, "timeOfDay":"Morning, Afternoon, Evening"},
    {"activity":"Go to an amusement park", "season":"Spring Summer Fall", "minPrice":30, "timeOfDay":"Morning, Afternoon, Evening"},
    {"activity":"Rent a convertible sports car and cruise around", "season":"Spring Summer Fall", "minPrice":200, "timeOfDay":"Morning, Afternoon, Evening, Night"},
    {"activity":"Restore an old piece of furniture together", "season":"Spring Summer Fall", "minPrice":20, "timeOfDay":"Morning, Afternoon, Evening"},
    {"activity":"Get creative with sidewalk chalk", "season":"Spring Summer", "minPrice":5, "timeOfDay":"Morning, Afternoon, Evening"},
    {"activity":"Try out a science expirement", "season":"Any season", "minPrice":5, "timeOfDay":"Morning, Afternoon, Evening"},
    {"activity":"Drive around looking for yard sales and see if you can find anything interesting", "season":"Spring Summer", "minPrice":5, "timeOfDay":"Morning, Afternoon, Evening"},
    {"activity":"Buy some modeling clay and see what you can make", "season":"Any season", "minPrice":5, "timeOfDay":"Morning, Afternoon, Evening"},
    {"activity":"Paint together with watercolors", "season":"Any season", "minPrice":5, "timeOfDay":"Morning, Afternoon, Evening"},
    {"activity":"Paint and build a model", "season":"Any season", "minPrice":20, "timeOfDay":"Morning, Afternoon, Evening"},
    {"activity":"Buy some Lego kits and put them together", "season":"Any season", "minPrice":20, "timeOfDay":"Morning, Afternoon, Evening"},
    {"activity":"Go to a flea market", "season":"Spring Summer", "minPrice":10, "timeOfDay":"Morning, Afternoon, Evening"},
    {"activity":"Make a time capsul", "season":"Spring Summer", "minPrice":0, "timeOfDay":"Morning, Afternoon, Evening"},
    {"activity":"Make a craft together", "season":"Any season", "minPrice":5, "timeOfDay":"Any time"},
    {"activity":"Go to a science center", "season":"Any season", "minPrice":10, "timeOfDay":"Morning, Afternoon, Evening"},
    {"activity":"Go to an art museum", "season":"Any season", "minPrice":0, "timeOfDay":"Morning, Afternoon, Evening"},
    {"activity":"See some standup comedy", "season":"Any season", "minPrice":20, "timeOfDay":"Evening"},
    {"activity":"Do a dinner theatre or murder mystery", "season":"Any season", "minPrice":100, "timeOfDay":"Evening"},
    {"activity":"Rent motorized schooters and drive around town", "season":"Spring Summer Fall", "minPrice":20, "timeOfDay":"Morning Afternoon Evening"},
    {"activity":"Do an animal encounter at a zoo", "season":"Spring Summer Fall", "minPrice":50, "timeOfDay":"Morning Afternoon Evening"},
    {"activity":"Go to a shooting range", "season":"Any season", "minPrice":20, "timeOfDay":"Morning Afternoon Evening"},
    {"activity":"Go to a demolition derby", "season":"Spring Summer Fall", "minPrice":30, "timeOfDay":"Afternoon Evening"},
    {"activity":"Build and launch a rocket together", "season":"Spring Summer Fall", "minPrice":10, "timeOfDay":"Morning Afternoon Evening"},
    {"activity":"Visit a national or state park", "season":"Spring Summer Fall", "minPrice":0, "timeOfDay":"Morning Afternoon Evening"},
    {"activity":"Get some coloring books and color", "season":"Any season", "minPrice":5, "timeOfDay":"Morning Afternoon Evening"},
    {"activity":"Go to a car show", "season":"Spring Summer Fall", "minPrice":0, "timeOfDay":"Morning Afternoon Evening"},
    {"activity":"Play disc golf", "season":"Spring Summer", "minPrice":0, "timeOfDay":"Morning Afternoon Evening"},
    {"activity":"Go to a local festival", "season":"Spring Summer", "minPrice":0, "timeOfDay":"Morning Afternoon Evening"},
    {"activity":"Go to a local fair", "season":"Spring Summer", "minPrice":0, "timeOfDay":"Morning Afternoon Evening"},
    {"activity":"Make origami together", "season":"Spring Summer", "minPrice":10, "timeOfDay":"Morning Afternoon Evening"},
    {"activity":"Do photography around town", "season":"Any season", "minPrice":0, "timeOfDay":"Morning Afternoon Evening"},
    {"activity":"Play badminton", "season":"Spring Summer", "minPrice":10, "timeOfDay":"Morning Afternoon Evening"},
    {"activity":"Go birdwatching", "season":"Spring Summer", "minPrice":0, "timeOfDay":"Morning Afternoon Evening"},
    {"activity":"Go jogging", "season":"Spring Summer", "minPrice":0, "timeOfDay":"Morning Afternoon Evening"},
    {"activity":"Skip rocks", "season":"Spring Summer", "minPrice":0, "timeOfDay":"Morning Afternoon Evening"},
    {"activity":"Write a song together", "season":"Any season", "minPrice":0, "timeOfDay":"Any time"},
    {"activity":"Download an augmented reality game on your phone and walk around playing the game", "season":"Any season", "minPrice":0, "timeOfDay":"Any time"},
    {"activity":"Exercise together", "season":"Any season", "minPrice":0, "timeOfDay":"Any time"},
    {"activity":"Watch airplanes take off from the airport", "season":"Any season", "minPrice":0, "timeOfDay":"Any time"},
    {"activity":"Do a book club together. First, pick a book for each other to read and then meet up and discuss them", "season":"Any season", "minPrice":0, "timeOfDay":"Any time"},
    {"activity":"Pain Easter eggs", "season":"Spring", "minPrice":5, "timeOfDay":"Any time"},
    {"activity":"Make matching t-shirts. You can iron things on shirts, paint them, etc.", "season":"Any season", "minPrice":10, "timeOfDay":"Any time"},
    {"activity":"Buy and read some comic books together.", "season":"Any season", "minPrice":10, "timeOfDay":"Any time"},
    {"activity":"Write a story together. One person writes a line, and then the next person writes the next line.", "season":"Any season", "minPrice":0, "timeOfDay":"Any time"},
    {"activity":"Go to a plan nursery and pick out a plant or two", "season":"Spring Summer", "minPrice":10, "timeOfDay":"Any time"},
    {"activity":"Watch a movie at a park", "season":"Spring Summer", "minPrice":0, "timeOfDay":"Any time"},
    {"activity":"Make some flip books together", "season":"Any season", "minPrice":5, "timeOfDay":"Any time"},
    {"activity":"Watch a movie and try to make memes from it", "season":"Any season", "minPrice":0, "timeOfDay":"Any time"},
    {"activity":"Write some letters to someone", "season":"Any season", "minPrice":5, "timeOfDay":"Any time"},
    {"activity":"Find a world record and try to break it", "season":"Any season", "minPrice":0, "timeOfDay":"Any time"},
    {"activity":"Do a themed photo shoot", "season":"Any season", "minPrice":0, "timeOfDay":"Any time"},
    {"activity":"Go paintballing", "season":"Spring Summer Fall", "minPrice":30, "timeOfDay":"Morning Afternoon Evening"},
    {"activity":"Ride the train somewhere", "season":"Any season", "minPrice":10, "timeOfDay":"Morning Afternoon Evening"},
    {"activity":"Buy some cheap RC cars and race them", "season":"Spring Summer", "minPrice":20, "timeOfDay":"Morning Afternoon Evening"},
    {"activity":"Make caramel apples", "season":"Fall", "minPrice":10, "timeOfDay":"Morning Afternoon Evening"},
    {"activity":"Go to a baseball game", "season":"Summer", "minPrice":10, "timeOfDay":"Afternoon Evening"},
    {"activity":"Make a gingerbread house", "season":"Winter", "minPrice":10, "timeOfDay":"Any time"},
    {"activity":"Go fishing", "season":"Spring Summer", "minPrice":5, "timeOfDay":"Early Morning Morning Afternoon Evening"}
]
